sense_emu/RTIMU.py
sense_emu/__init__.py
sense_emu/common.py
sense_emu/dump.py
sense_emu/gschemas.compiled
sense_emu/gui.py
sense_emu/humidity.py
sense_emu/i18n.py
sense_emu/imu.py
sense_emu/lock.py
sense_emu/main_window.ui
sense_emu/menu.ui
sense_emu/orientation.png
sense_emu/pixel_grid.png
sense_emu/play.py
sense_emu/prefs_dialog.ui
sense_emu/pressure.py
sense_emu/record.py
sense_emu/screen.py
sense_emu/sense_emu.png
sense_emu/sense_emu_gui.png
sense_emu/sense_emu_gui.svg
sense_emu/sense_hat.py
sense_emu/sense_hat_text.png
sense_emu/sense_hat_text.txt
sense_emu/stick.py
sense_emu/terminal.py
sense_emu/examples/advanced/joystick_events.py
sense_emu/examples/advanced/sensor_menu.py
sense_emu/examples/basic/humidity.py
sense_emu/examples/basic/temperature.py
sense_emu/examples/intermediate/bar_graph.py
sense_emu/examples/intermediate/joystick_loop.py
sense_emu/examples/intermediate/line_graph.py
sense_emu/examples/intermediate/plumb_line.py
sense_emu/examples/intermediate/rainbow.py
sense_emu/locale/en_US/LC_MESSAGES/sense-emu.mo
sense_emu-1.2.1.dist-info/LICENSE.txt
sense_emu-1.2.1.dist-info/METADATA
sense_emu-1.2.1.dist-info/WHEEL
sense_emu-1.2.1.dist-info/entry_points.txt
sense_emu-1.2.1.dist-info/top_level.txt
sense_emu-1.2.1.dist-info/RECORD
