Metadata-Version: 2.1
Name: sense-emu
Version: 1.2.1
Summary: The Raspberry Pi Sense HAT Emulator library
Home-page: https://sense-emu.readthedocs.io/
Author: Raspberry Pi Foundation
Author-email: info@raspberrypi.org
License: GPL-2.0-or-later
Project-URL: Documentation, https://sense-emu.readthedocs.io/
Project-URL: Source Code, https://github.com/astro-pi/python-sense-emu
Project-URL: Issue Tracker, https://github.com/astro-pi/python-sense-emu/issues
Keywords: raspberrypi sense hat
Platform: UNKNOWN
Classifier: Development Status :: 5 - Production/Stable
Classifier: Environment :: Console
Classifier: Environment :: X11 Applications :: GTK
Classifier: Intended Audience :: Developers
Classifier: License :: OSI Approved :: GNU General Public License v2 or later (GPLv2+)
Classifier: License :: OSI Approved :: GNU Lesser General Public License v2 or later (LGPLv2+)
Classifier: Operating System :: POSIX :: Linux
Classifier: Operating System :: MacOS :: MacOS X
Classifier: Operating System :: Microsoft :: Windows
Classifier: Programming Language :: Python :: 2.7
Classifier: Programming Language :: Python :: 3.2
Classifier: Programming Language :: Python :: 3.3
Classifier: Programming Language :: Python :: 3.4
Classifier: Programming Language :: Python :: 3.5
Classifier: Topic :: Scientific/Engineering
Provides-Extra: doc
Provides-Extra: test
